Workbook

Sheet README
B2: MG-C1 ENERGY TRANSFORMER - BILL OF MATERIALS
B3: Flux-modulated magnetic gear stage (MG-1) driven as a human/low-speed charging generator
B5: Revision | C5: 0.1 - companion to MG-1_drawing_set.pdf (15 sheets) and the MG1_*.scad parametric source
B6: Programme | C6: CBJG LLC · Benchtop Motor Program. SAFE-01 reset semantics per GitHub issue #14 (canonical).
B7: Status | C7: BENCH INSTRUMENT + demonstrator. Not a product. Not for production.
B9: What this builds | C9: A hand-crank (or slow wind / low-head flow) charger. The slow, high-torque input turns the
C10: MG-1 low-speed port; MG-1 steps speed UP 4.5:1 into a low-kV hub motor used as a generator;
C11: a 3-phase bridge, a buck-boost charge controller and a LiFePO4 buffer pack feed a USB-PD port.
B13: Honest headline | C13: ~12 W at the USB-C port at a 90 rpm crank. See the 'Energy budget' tab - it is a live model.
B14: What limits it | C14: NOT the operator. Sustained one-hand cranking is 54 +/- 14 W (Jansen & Slob, 2003).
C15: MG-1's pull-out torque caps mechanical input at ~23 W at 90 rpm. The gear is the bottleneck.
C16: Torque scales with active volume at 12-20 N.m/L, so more power means a physically bigger gear.
B18: No over-unity | C18: P_out <= P_in at all times. Gate 4 (sheet 12) is a MANDATORY falsification test:
C19: three ports measured, cells cross-calibrated and SWAPPED between ports. Required result:
C20: no excess energy. Any reading suggesting otherwise is an instrumentation error, and the
C21: three-port method exists specifically so that error has nowhere to hide.
B23: Build tiers | C23: CHG = everything needed to build and run the charger
C24: INST = adds the three-port instrumentation for Gates 1-4
C25: OPT = variant sweeps (V2/V3 pole pieces), the designed power board, rotary torque sensors
B27: Cost basis | C27: USD, mid-2026, single-unit hobby quantities unless a pack size is stated. Prices move;
C28: the 'Unit cost' column is an input, not a fact. Sources for the researched lines are on
C29: the 'Sources' tab. Freight, tax and contingency rates are assumptions on 'Roll-up'.
B31: Printed parts | C31: Costed by filament mass against a single rate cell on 'Roll-up'. PETG or ASA. NEVER PLA:
C32: PLA creeps at 55 C, a crept air gap is a rotor crash.
B33: Critical BOM note | C33: Line C1 - the 22 pole-piece bolts MUST be plain low-carbon steel. A2/A4 stainless is
C34: austenitic and near-non-magnetic; fit it and the gear makes almost no torque.

Sheet BOM
B2: MG-C1 BILL OF MATERIALS - all line items
B3: Printed-part unit costs are formulas: mass(g)/1000 x the filament rate on Roll-up!C7.
B5: Sect | C5: Ref | D5: Item | E5: Spec / part number | F5: Qty | G5: Unit | H5: Unit cost (USD est.) | I5: Extended (USD) | J5: Tier | K5: Supplier | L5: Notes
B6: A | C6: PRINTED PARTS (PETG or ASA - never PLA)
B7: A | C7: A1 | D7: HS rotor carrier | E7: MG1_rotor.scad, which="hs", 8 thk, d120 | F7: 1 | G7: ea | H7: =95/1000*Roll_up_rate -> 2.09 | I7: =F7*H7 -> 2.09 | J7: CHG | K7: self-printed | L7: 95 g. Pockets UP, 100% infill under pockets.
B8: A | C8: A2 | D8: LS rotor carrier | E8: MG1_rotor.scad, which="ls", 8 thk, d120 | F8: 1 | G8: ea | H8: =95/1000*Roll_up_rate -> 2.09 | I8: =F8*H8 -> 2.09 | J8: CHG | K8: self-printed | L8: 95 g. Metal hub insert or through-pin at the shaft.
B9: A | C9: A3 | D9: Modulator plate + reaction arm | E9: MG1_modulator.scad, variant=1, 12 thk | F9: 1 | G9: ea | H9: =150/1000*Roll_up_rate -> 3.3 | I9: =F9*H9 -> 3.3 | J9: CHG | K9: self-printed | L9: 150 g. Arm SOLID, 6 perimeters - it is a measurement datum.
B10: A | C10: A4 | D10: Frame end plate | E10: MG1_frame.scad, part="frame", 6 thk | F10: 2 | G10: ea | H10: =65/1000*Roll_up_rate -> 1.43 | I10: =F10*H10 -> 2.86 | J10: CHG | K10: self-printed | L10: 65 g each. Bearing seat takes a bonded steel sleeve.
B11: A | C11: A5 | D11: Gap shim, trial only | E11: MG1_frame.scad, part="shim", 0.10 | F11: 6 | G11: ea | H11: =2/1000*Roll_up_rate -> 0.044 | I11: =F11*H11 -> 0.264 | J11: OPT | K11: self-printed | L11: 2 g each. Trial fit only - real sweep uses metal shim stock.
B12: A | C12: A6 | D12: Crank housing + pillow-block mount | E12: derived from frame plate PCD | F12: 1 | G12: set | H12: =180/1000*Roll_up_rate -> 3.96 | I12: =F12*H12 -> 3.96 | J12: CHG | K12: self-printed | L12: 180 g.
B13: A | C13: A7 | D13: Burst shroud frame | E13: holds the polycarbonate window | F13: 1 | G13: ea | H13: =120/1000*Roll_up_rate -> 2.64 | I13: =F13*H13 -> 2.64 | J13: CHG | K13: self-printed | L13: 120 g. Interlock switch pocket moulded in.
B14: A | C14: A8 | D14: Assembly jig plates | E14: threaded-rod walk-in jig, sheet 3 step 7 | F14: 2 | G14: ea | H14: =30/1000*Roll_up_rate -> 0.66 | I14: =F14*H14 -> 1.32 | J14: CHG | K14: self-printed | L14: 60 g total.
B15: A | C15: A9 | D15: Generator mount cradle | E15: 6.5in hub motor stator clamp | F15: 1 | G15: ea | H15: =140/1000*Roll_up_rate -> 3.08 | I15: =F15*H15 -> 3.08 | J15: CHG | K15: self-printed | L15: 140 g.
B17: B | C17: MAGNETS & BONDING
B18: B | C18: B1 | D18: Neodymium block magnet | E18: N42 nickel, 20 x 10 x 5 mm, Q-20-10-05-N | F18: 45 | G18: ea | H18: 1.4 | I18: =F18*H18 -> 63 | J18: CHG | K18: supermagnete | L18: 38 used (20 HS + 18 LS) + 7 spares. EUR1.26 ea from 40 pcs.
B19: B | C19: B2 | D19: Magnet keeper / storage box | E19: steel-lined, separated cells | F19: 1 | G19: ea | H19: 8 | I19: =F19*H19 -> 8 | J19: CHG | K19: generic | L19: Loose N42 blocks are projectiles. Store separated.
B20: B | C20: B3 | D20: Cyanoacrylate, thick gel | E20: 20 g | F20: 2 | G20: ea | H20: 7 | I20: =F20*H20 -> 14 | J20: CHG | K20: generic | L20: Seat DRY and probe polarity BEFORE any adhesive.
B21: B | C21: B4 | D21: CA activator | E21: 150 ml | F21: 1 | G21: ea | H21: 8 | I21: =F21*H21 -> 8 | J21: CHG | K21: generic
B22: B | C22: B5 | D22: Isopropyl alcohol | E22: 500 ml, pocket prep | F22: 1 | G22: ea | H22: 6 | I22: =F22*H22 -> 6 | J22: CHG | K22: generic
B24: C | C24: GAP-CRITICAL METAL, FASTENERS & SHAFTING
B25: C | C25: C1 | D25: Pole-piece bolt | E25: M8 x 25, grade 4.8 LOW-CARBON STEEL, plain | F25: 26 | G25: ea | H25: 0.35 | I25: =F25*H25 -> 9.1 | J25: CHG | K25: fastener supplier | L25: CRITICAL: must be magnetic plain steel. A2/A4 stainless is austenitic and near-non-magnetic - it will produce almost zero torque.
B26: C | C26: C2 | D26: M8 flat washer | E26: plain steel | F26: 26 | G26: ea | H26: 0.05 | I26: =F26*H26 -> 1.3 | J26: CHG | K26: fastener supplier
B27: C | C27: C3 | D27: Tie rod stock | E27: M5 x 1000 threaded rod, A2 stainless | F27: 1 | G27: ea | H27: 6 | I27: =F27*H27 -> 6 | J27: CHG | K27: fastener supplier | L27: Cut 4 x 53.6 mm. Stainless is fine here - it sits outside the flux path.
B28: C | C28: C4 | D28: M5 nyloc nut | E28: A2 | F28: 16 | G28: ea | H28: 0.12 | I28: =F28*H28 -> 1.92 | J28: CHG | K28: fastener supplier
B29: C | C29: C5 | D29: Aluminium standoff tube | E29: 9.0 OD x 5.3 ID x 300 mm | F29: 1 | G29: ea | H29: 9 | I29: =F29*H29 -> 9 | J29: CHG | K29: metal supplier | L29: Cut 4 x 41.6 mm. THESE set the two 0.80 mm air gaps, not the plastic.
B30: C | C30: C6 | D30: Deep-groove ball bearing | E30: 608ZZ, 8 x 22 x 7, 10-pack | F30: 1 | G30: pk | H30: 20.65 | I30: =F30*H30 -> 20.65 | J30: CHG | K30: Amazon (NSK) | L30: 4 used, 6 spare. USD2.07 each.
B31: C | C31: C7 | D31: Steel bearing sleeve | E31: 22.0 OD, 1.2 wall, 30 mm long | F31: 2 | G31: ea | H31: 12 | I31: =F31*H31 -> 24 | J31: CHG | K31: metal supplier | L31: Bonded into the printed seat. NEVER run a 608 directly in plastic.
B32: C | C32: C8 | D32: Ground shaft | E32: d8 h6 x 100 mm, 1045 or stainless | F32: 2 | G32: ea | H32: 7 | I32: =F32*H32 -> 14 | J32: CHG | K32: metal supplier | L32: HS shaft to generator, LS shaft to crank.
B33: C | C33: C9 | D33: Key steel | E33: 3 x 3 x 100 mm | F33: 1 | G33: ea | H33: 4 | I33: =F33*H33 -> 4 | J33: CHG | K33: metal supplier
B34: C | C34: C10 | D34: Shim stock assortment | E34: brass/steel 0.05-0.20 mm | F34: 1 | G34: set | H34: 12 | I34: =F34*H34 -> 12 | J34: CHG | K34: metal supplier | L34: The real Gate 1 gap sweep: 0.60/0.80/1.00/1.20.
B35: C | C35: C11 | D35: M3 mild steel rod | E35: 3 mm x 1 m, for V2 bundled pole pieces | F35: 1 | G35: ea | H35: 5 | I35: =F35*H35 -> 5 | J35: OPT | K35: metal supplier | L35: V2 variant: 11 x 7-off M3 bundles, ~7x lower eddy loss.
B36: C | C36: C12 | D36: Laminated steel sheet | E36: 0.35 mm, 100 x 100, for V3 pole pieces | F36: 1 | G36: ea | H36: 18 | I36: =F36*H36 -> 18 | J36: OPT | K36: metal supplier | L36: V3 variant: stacked laminations, approaches literature loss.
B38: D | C38: DRIVE, CRANK, GENERATOR & GUARDING
B39: D | C39: D1 | D39: Hub motor used as PMSG | E39: 6.5in hoverboard hub motor, 36 V 250 W class | F39: 1 | G39: ea | H39: 106.99 | I39: =F39*H39 -> 106.99 | J39: CHG | K39: Monster Scooter Parts | L39: kV ~13.4 rpm/V from vehicle data - very low kV is exactly what a slow charger needs. AliExpress ~USD70 alternative.
B40: D | C40: D2 | D40: Hand crank arm | E40: 150 mm, rotating knob, d8 bore | F40: 1 | G40: ea | H40: 14 | I40: =F40*H40 -> 14 | J40: CHG | K40: generic | L40: 150 mm x 16 N of hand force = 2.4 N.m, the design point.
B41: D | C41: D3 | D41: Pillow block bearing | E41: KFL08 flange, d8 | F41: 2 | G41: ea | H41: 6 | I41: =F41*H41 -> 12 | J41: CHG | K41: generic | L41: Carries crank side load off the printed plate.
B42: D | C42: D4 | D42: Flexible jaw coupling | E42: 8 mm - 8 mm, backlash-free | F42: 2 | G42: ea | H42: 8 | I42: =F42*H42 -> 16 | J42: CHG | K42: generic | L42: Isolates shaft misalignment from the air gap.
B43: D | C43: D5 | D43: Aluminium extrusion | E43: 2020 T-slot, 1 m | F43: 2 | G43: ea | H43: 9 | I43: =F43*H43 -> 18 | J43: CHG | K43: generic | L43: Bench frame.
B44: D | C44: D6 | D44: Bracket + T-nut set | E44: 2020 corner brackets, M5 | F44: 1 | G44: set | H44: 14 | I44: =F44*H44 -> 14 | J44: CHG | K44: generic
B45: D | C45: D7 | D45: Polycarbonate sheet | E45: 3 mm, 300 x 300, burst shroud window | F45: 1 | G45: ea | H45: 18 | I45: =F45*H45 -> 18 | J45: CHG | K45: plastics supplier | L45: PC, not acrylic. Acrylic shatters.
B46: D | C46: D8 | D46: Shroud position switch | E46: SPDT roller lever, NC wiring | F46: 1 | G46: ea | H46: 6 | I46: =F46*H46 -> 6 | J46: CHG | K46: generic | L46: Wires into the SAFE-01 enclosure interlock (issue #14 canonical).
B47: D | C47: D9 | D47: Baseboard | E47: 18 mm ply, 400 x 300 | F47: 1 | G47: ea | H47: 10 | I47: =F47*H47 -> 10 | J47: CHG | K47: generic
B49: E | C49: ENERGY TRANSFORMER - POWER CONVERSION CHAIN
B50: E | C50: E1 | D50: Schottky rectifier diode | E50: MBR20100CT TO-220, 3-phase bridge | F50: 6 | G50: ea | H50: 0.9 | I50: =F50*H50 -> 5.4 | J50: CHG | K50: Mouser/DigiKey | L50: Tier A bridge. At ~30 V bus the 2 x 0.4 V drop costs only ~3%.
B51: E | C51: E2 | D51: Heatsink + insulator kit | E51: TO-220, 6 off | F51: 1 | G51: set | H51: 7 | I51: =F51*H51 -> 7 | J51: CHG | K51: Mouser/DigiKey
B52: E | C52: E3 | D52: Ideal-diode bridge controller | E52: LT4320IDD-1, 3 off for 3-phase | F52: 3 | G52: ea | H52: 4.07 | I52: =F52*H52 -> 12.21 | J52: OPT | K52: Analog Devices | L52: Tier B upgrade. ~99.5% vs ~84% for a diode bridge at low line voltage. Only worth it if the bus falls below ~10 V.
B53: E | C53: E4 | D53: N-channel MOSFET | E53: 40 V logic-level, low Rds(on), for E3 | F53: 6 | G53: ea | H53: 1.2 | I53: =F53*H53 -> 7.2 | J53: OPT | K53: Mouser/DigiKey
B54: E | C54: E5 | D54: Bulk electrolytic capacitor | E54: 470 uF 63 V, low ESR | F54: 2 | G54: ea | H54: 2.5 | I54: =F54*H54 -> 5 | J54: CHG | K54: Mouser/DigiKey | L54: Ripple smoothing only. NOT an energy sink - see E13.
B55: E | C55: E6 | D55: Transient clamp | E55: SMBJ33A TVS + MOV | F55: 1 | G55: set | H55: 2 | I55: =F55*H55 -> 2 | J55: CHG | K55: Mouser/DigiKey | L55: Crank stalls and rotor slip make fast dV/dt events.
B56: E | C56: E7 | D56: Buck-boost charge controller | E56: LTC4020EUHF, 4.5-55 V in, up to 55 V out | F56: 1 | G56: ea | H56: 6.79 | I56: =F56*H56 -> 6.79 | J56: OPT | K56: Analog Devices | L56: Tier B designed board. USD6.79 at 1ku list.
B57: E | C57: E8 | D57: Buck-boost MPPT charge module | E57: DC 8-60 V in, CC/CV out, adjustable | F57: 1 | G57: ea | H57: 16 | I57: =F57*H57 -> 16 | J57: CHG | K57: generic module | L57: Tier A. Buy this first; design E7 only after Gate 3.
B58: E | C58: E9 | D58: LiFePO4 buffer pack | E58: 4S1P 18650/26650, 12.8 V 3 Ah, ~38 Wh | F58: 1 | G58: ea | H58: 34 | I58: =F58*H58 -> 34 | J58: CHG | K58: generic | L58: MANDATORY, not optional. A phone will not negotiate charge from a fluctuating hand-crank source. The cell decouples them.
B59: E | C59: E10 | D59: BMS | E59: 4S LiFePO4, 20 A, balance + protect | F59: 1 | G59: ea | H59: 9 | I59: =F59*H59 -> 9 | J59: CHG | K59: generic
B60: E | C60: E11 | D60: USB-PD source board | E60: 12 V in, 20-45 W PD 3.0 out, USB-C | F60: 1 | G60: ea | H60: 12 | I60: =F60*H60 -> 12 | J60: CHG | K60: generic | L60: A PD SOURCE, not a 'trigger'/'decoy' sink board. Those are the opposite direction.
B61: E | C61: E12 | D61: Panel volt/amp meter | E61: 0-100 V / 0-10 A, bus monitor | F61: 1 | G61: ea | H61: 8 | I61: =F61*H61 -> 8 | J61: CHG | K61: generic
B62: E | C62: E13 | D62: Dump / brake resistor | E62: 10 ohm 50 W, chassis mount | F62: 1 | G62: ea | H62: 6 | I62: =F62*H62 -> 6 | J62: CHG | K62: Mouser/DigiKey | L62: Regen pushes the bus ABOVE nominal. The capacitor bank is not a sink.
B63: E | C63: E14 | D63: Dump chopper | E63: N-FET + comparator + gate resistor | F63: 1 | G63: set | H63: 4 | I63: =F63*H63 -> 4 | J63: CHG | K63: Mouser/DigiKey
B64: E | C64: E15 | D64: Fuse holder + fuse | E64: inline blade, 10 A | F64: 1 | G64: set | H64: 4 | I64: =F64*H64 -> 4 | J64: CHG | K64: generic | L64: At the +ve terminal, per the existing build gate.
B65: E | C65: E16 | D65: Reverse-block diode | E65: Schottky 60 V 5 A, buffer isolation | F65: 2 | G65: ea | H65: 1 | I65: =F65*H65 -> 2 | J65: CHG | K65: Mouser/DigiKey
B66: E | C66: E17 | D66: Connector set | E66: XT60 pair + Anderson PP15 | F66: 1 | G66: set | H66: 8 | I66: =F66*H66 -> 8 | J66: CHG | K66: generic
B67: E | C67: E18 | D67: Silicone wire + heatshrink | E67: 18 AWG, 5 m, assorted shrink | F67: 1 | G67: set | H67: 10 | I67: =F67*H67 -> 10 | J67: CHG | K67: generic
B68: E | C68: E19 | D68: Enclosure | E68: ABS 200 x 120 x 75, IP54 | F68: 1 | G68: ea | H68: 16 | I68: =F68*H68 -> 16 | J68: CHG | K68: generic
B69: E | C69: E20 | D69: PCB | E69: 2-layer, 100 x 80, 5 off | F69: 1 | G69: pk | H69: 12 | I69: =F69*H69 -> 12 | J69: CHG | K69: JLCPCB/PCBWay
B70: E | C70: E21 | D70: Mode switch | E70: 3-position: OFF / CHARGE / LOAD | F70: 1 | G70: ea | H70: 4 | I70: =F70*H70 -> 4 | J70: CHG | K70: generic
B71: E | C71: E22 | D71: Pack thermistor | E71: 10k NTC, bonded to the buffer pack | F71: 1 | G71: ea | H71: 2 | I71: =F71*H71 -> 2 | J71: CHG | K71: generic
B73: F | C73: INSTRUMENTATION (Gates 1-4, three-port energy balance)
B74: F | C74: F1 | D74: Load cell | E74: 5 kg straight bar + HX711 amplifier | F74: 3 | G74: ea | H74: 9 | I74: =F74*H74 -> 27 | J74: INST | K74: generic | L74: Reaction-arm and torque-arm method. tau = F x r.
B75: F | C75: F2 | D75: Inline rotary torque sensor | E75: 0-5 N.m, +/-0.5% FS | F75: 2 | G75: ea | H75: 260 | I75: =F75*H75 -> 520 | J75: OPT | K75: instrument supplier | L75: The correct instrument, and the single biggest cost in the programme. Start with F1 and upgrade at Gate 3.
B76: F | C76: F3 | D76: Magnetic rotary encoder | E76: AS5047P breakout, SPI | F76: 2 | G76: ea | H76: 18 | I76: =F76*H76 -> 36 | J76: INST | K76: generic | L76: Slip observer: compare w_ls against w_hs / 4.5.
B77: F | C77: F4 | D77: Current sense amplifier | E77: INA240A2 breakout | F77: 3 | G77: ea | H77: 7 | I77: =F77*H77 -> 21 | J77: INST | K77: generic
B78: F | C78: F5 | D78: Thermistor | E78: 10k NTC on an outer M8 bolt head | F78: 3 | G78: ea | H78: 2 | I78: =F78*H78 -> 6 | J78: INST | K78: generic | L78: T_mod is a real logged channel, and the eddy-heating witness.
B79: F | C79: F6 | D79: MCU board | E79: STM32G474 - EXISTING CBJG hardware | F79: 1 | G79: ea | H79: 0 | I79: =F79*H79 -> 0 | J79: INST | K79: already owned | L79: Reuse, do not redesign. No new silicon required.
B80: F | C80: F7 | D80: SD logging module | E80: SPI, 10 kHz sample target | F80: 1 | G80: ea | H80: 6 | I80: =F80*H80 -> 6 | J80: INST | K80: generic
B81: F | C81: F8 | D81: Dead-weight calibration set | E81: 0.5 / 1 / 2 kg, class M1 | F81: 1 | G81: set | H81: 28 | I81: =F81*H81 -> 28 | J81: INST | K81: instrument supplier | L81: Both cells calibrated against the SAME reference, then SWAPPED between ports at Gate 4.
B82: F | C82: F9 | D82: Optical tachometer | E82: photo-interrupter + slotted disc | F82: 2 | G82: ea | H82: 8 | I82: =F82*H82 -> 16 | J82: INST | K82: generic | L82: Independent speed check on the encoders.
B84: G | C84: CONSUMABLES, TOOLING & SAFETY
B85: G | C85: G1 | D85: PETG filament | E85: 1 kg spool | F85: 2 | G85: ea | H85: 22 | I85: =F85*H85 -> 44 | J85: CHG | K85: generic | L85: ~900 g of parts. Budget for reprints - you will reprint.
B86: G | C86: G2 | D86: ASA filament | E86: 1 kg spool | F86: 1 | G86: ea | H86: 28 | I86: =F86*H86 -> 28 | J86: OPT | K86: generic | L86: If ambient or modulator temperature exceeds PETG's comfort band.
B87: G | C87: G3 | D87: Magnetic pole probe | E87: Mark II Magnaprobe | F87: 1 | G87: ea | H87: 30 | I87: =F87*H87 -> 30 | J87: CHG | K87: Indigo Instruments | L87: Confirms every block's polarity before bonding. The #1 build failure is one reversed block.
B88: G | C88: G4 | D88: Hall probe module | E88: A1302 / A1324 breakout | F88: 1 | G88: ea | H88: 6 | I88: =F88*H88 -> 6 | J88: CHG | K88: generic | L88: Quantitative check to back up the probe.
B89: G | C89: G5 | D89: Torque wrench | E89: 1-6 N.m, 1/4in drive | F89: 1 | G89: ea | H89: 32 | I89: =F89*H89 -> 32 | J89: CHG | K89: generic | L89: Modulator bolts go to SNUG only - the plate is plastic.
B90: G | C90: G6 | D90: Feeler gauge set | E90: 0.02-1.00 mm | F90: 1 | G90: set | H90: 9 | I90: =F90*H90 -> 9 | J90: CHG | K90: generic | L90: Air-gap verification at four points per gap.
B91: G | C91: G7 | D91: Torque arm / breakaway wrench | E91: 0-5 N.m dial, Gate 1 static pull-out | F91: 1 | G91: ea | H91: 45 | I91: =F91*H91 -> 45 | J91: CHG | K91: generic | L91: Gate 1: measure breakaway torque and angle, 10 repeats.
B92: G | C92: G8 | D92: Threaded rod, long | E92: M5 x 300, 4 off, assembly jig | F92: 1 | G92: set | H92: 8 | I92: =F92*H92 -> 8 | J92: CHG | K92: fastener supplier | L92: Diagonal pairs, a quarter turn at a time. An unrestrained rotor free-flies.
B93: G | C93: G9 | D93: Threadlocker | E93: Loctite 243, 10 ml | F93: 1 | G93: ea | H93: 9 | I93: =F93*H93 -> 9 | J93: CHG | K93: generic
B94: G | C94: G10 | D94: IR thermometer | E94: -50 to 380 C | F94: 1 | G94: ea | H94: 18 | I94: =F94*H94 -> 18 | J94: CHG | K94: generic | L94: Frame temperature exit criterion is < 50 C.
B95: G | C95: G11 | D95: PPE | E95: safety glasses + nitrile gloves | F95: 1 | G95: set | H95: 12 | I95: =F95*H95 -> 12 | J95: CHG | K95: generic | L95: Neodymium chips are sharp and the dust is flammable.
B96: G | C96: G12 | D96: Ferrofluid, QC use only | E96: EFH1 class, 10 ml | F96: 1 | G96: ea | H96: 30 | I96: =F96*H96 -> 30 | J96: CHG | K96: Ferrotec / educational | L96: Polarity MAPPING, never in the gap. A thin film on a PET transparency over the assembled rotor face images all 20 (HS) or 18 (LS) poles at once; a reversed block breaks the alternation visibly. Per MG-3: do NOT flood the air gaps.

Sheet Roll-up
B2: COST ROLL-UP
B4: Assumptions
B5: Filament rate | C5: $/kg | D5: 22 | G5: PETG, 1 kg spool. Drives every printed-part unit cost.
B6: Freight | C6: % of subtotal | D6: 0.08 | G6: Many small suppliers; assume 8%.
B7: Sales tax | C7: % of subtotal | D7: 0.0825 | G7: TX combined rate assumed - VERIFY for your address.
B8: Contingency | C8: % of subtotal | D8: 0.12 | G8: Reprints, one cooked module, a shorted FET.
B9: EUR to USD | C9: rate | D9: 1.09 | G9: Used for the supermagnete magnet price.
B12: Subtotal by section
B13: A PRINTED PARTS (PETG or ASA - never PLA) | D13: =SUMIFS(BOM!$I$6:$I$97,BOM!$B$6:$B$97,"A") -> 21.604
B14: B MAGNETS & BONDING | D14: =SUMIFS(BOM!$I$6:$I$97,BOM!$B$6:$B$97,"B") -> 99
B15: C GAP-CRITICAL METAL, FASTENERS & SHAFTING | D15: =SUMIFS(BOM!$I$6:$I$97,BOM!$B$6:$B$97,"C") -> 124.97
B16: D DRIVE, CRANK, GENERATOR & GUARDING | D16: =SUMIFS(BOM!$I$6:$I$97,BOM!$B$6:$B$97,"D") -> 214.99
B17: E ENERGY TRANSFORMER - POWER CONVERSION CHAIN | D17: =SUMIFS(BOM!$I$6:$I$97,BOM!$B$6:$B$97,"E") -> 192.6
B18: F INSTRUMENTATION (Gates 1-4, three-port energy balance) | D18: =SUMIFS(BOM!$I$6:$I$97,BOM!$B$6:$B$97,"F") -> 660
B19: G CONSUMABLES, TOOLING & SAFETY | D19: =SUMIFS(BOM!$I$6:$I$97,BOM!$B$6:$B$97,"G") -> 271
B20: ALL LINE ITEMS | D20: =SUM(D13:D19) -> 1584.164
B23: Build tiers
B24: Tier | C24: Scope | D24: Hardware subtotal | E24: + freight & tax | F24: + contingency | G24: DELIVERED TOTAL | H24: What you get
B25: 1 | C25: CHARGER | D25: =SUMIFS(BOM!$I$6:$I$97,BOM!$J$6:$J$97,"CHG") -> 846.7 | E25: =D25*(1+$D$6+$D$7) -> 984.28875 | F25: =E25+D25*$D$8 -> 1085.8927 | G25: =F25 -> 1085.8927 | H25: Working charger: prints, magnets, metal stack, generator, crank, guarding, power chain, core tooling.
B26: 2 | C26: INSTRUMENTED | D26: =SUMIFS(BOM!$I$6:$I$97,BOM!$J$6:$J$97,"CHG")+SUMIFS(BOM!$I$6:$I$97,BOM!$J$6:$J$97,"INST") -> 986.7 | E26: =D26*(1+$D$6+$D$7) -> 1147.0387 | F26: =E26+D26*$D$8 -> 1265.4427 | G26: =F26 -> 1265.4427 | H26: Adds three-port sensing, encoders, logging and dead-weight calibration - Gates 1-4 become runnable.
B27: 3 | C27: FULL RESEARCH | D27: =SUMIFS(BOM!$I$6:$I$97,BOM!$J$6:$J$97,"CHG")+SUMIFS(BOM!$I$6:$I$97,BOM!$J$6:$J$97,"INST")+SUMIFS(BOM!$I$6:$I$97,BOM!$J$6:$J$97,"OPT") -> 1584.164 | E27: =D27*(1+$D$6+$D$7) -> 1841.5907 | F27: =E27+D27*$D$8 -> 2031.6903 | G27: =F27 -> 2031.6903 | H27: Adds V2/V3 pole-piece sweep, the LTC4020/LT4320 designed board, and rotary torque sensors.
B30: Note | C30: Tier 3 is dominated by ONE line: F2, the pair of rotary torque sensors. Start on Tier 2 load cells, upgrade at Gate 3 only if the load-cell uncertainty band is too wide to close the energy balance.

Sheet Energy budget
B2: ENERGY BUDGET - live model
B3: Change the blue input cells. Everything else is a formula. No hardcoded results.
B4: Inputs
B5: Crank torque at LS port | C5: N.m | D5: 2.4 | H5: Design point. 150 mm crank arm x ~16 N of hand force.
B6: Crank speed at LS port | C6: rpm | D6: 90 | H6: Comfortable sustained one-hand cranking band is 60-120 rpm.
B7: Gear ratio |G| | C7: - | D7: 4.5 | H7: p_out/p_in = 9/2. Counter-rotating.
B8: Generator kV | C8: rpm/V | D8: 13.4 | H8: 6.5in hub motor, derived from 165 mm wheel at ~15 km/h on 36 V.
B9: MG-1 LS pull-out, low | C9: N.m | D9: 1.8 | H9: 12 N.m/L on 0.150 L active volume.
B10: MG-1 LS pull-out, high | C10: N.m | D10: 3 | H10: 20 N.m/L on 0.150 L active volume.
B12: Derived operating point
B13: LS angular velocity | C13: rad/s | D13: =2*PI()*D6/60 -> 9.424778
B14: Mechanical input power | C14: W | D14: =D5*D13 -> 22.619467 | H14: tau x omega at the crank. THIS is the ceiling, not the operator.
B15: HS shaft speed | C15: rpm | D15: =D6*D7 -> 405 | H15: Into the generator.
B16: HS shaft torque | C16: N.m | D16: =D5/D7 -> 0.53333333
B17: Generator line back-EMF | C17: V | D17: =D15/D8 -> 30.223881 | H17: Sets the rectifier and buck-boost input window.
B18: Modulator field frequency | C18: Hz | D18: =550*D15/3000 -> 74.25 | H18: 550 Hz at 3000 rpm HS scales linearly with speed.
B19: Eddy loss vs rated speed | C19: x | D19: =(D18/550)^2 -> 0.018225 | H19: Loss scales as f^2 - the charger runs in the gear's best loss regime.
B21: Conversion chain
B22: Stage | C22: Efficiency | D22: Loss (W) | E22: Power out (W) | H22: Why this number
B23: Magnetic gear MG-1, V1 solid bolts | C23: 0.9 | D23: =D14*(1-C23) -> 2.2619467 | E23: =D14*C23 -> 20.35752 | H23: At 90 rpm crank the modulator field is only ~74 Hz. Eddy loss scales as f^2, so it is ~1.8% of the rated-speed figure. Bearing and magnet drag dominate here.
B24: Hub motor as PMSG at ~405 rpm | C24: 0.75 | D24: =E23*(1-C24) -> 5.0893801 | E24: =E23*C24 -> 15.26814 | H24: Copper-loss dominated at low speed: back-EMF is small relative to winding resistance. This is the worst stage in the chain.
B25: 3-phase Schottky bridge, ~30 V bus | C25: 0.97 | D25: =E24*(1-C25) -> 0.45804421 | E25: =E24*C25 -> 14.810096 | H25: 2 x 0.4 V drop on a 30 V bus. Swap to LT4320 ideal-diode bridge only if the bus falls below ~10 V.
B26: Buck-boost charge controller | C26: 0.93 | D26: =E25*(1-C26) -> 1.0367067 | E26: =E25*C26 -> 13.773389 | H26: MPPT-style CC/CV into the buffer pack. Module (Tier A) or LTC4020 board (Tier B).
B27: LiFePO4 buffer pack round trip | C27: 0.94 | D27: =E26*(1-C27) -> 0.82640336 | E27: =E26*C27 -> 12.946986 | H27: The cost of decoupling an intermittent source from a device that demands a stable one. Not optional.
B28: USB-PD source stage | C28: 0.93 | D28: =E27*(1-C28) -> 0.90628902 | E28: =E27*C28 -> 12.040697 | H28: 12.8 V pack to 5/9/12 V PD. A real PD source, not a trigger board.
B29: OVERALL | C29: =E28/D14 -> 0.53231568 | D29: =SUM(D23:D28) -> 10.57877 | E29: =E28 -> 12.040697 | H29: Watts delivered at the USB-C port.
B31: What that actually charges
B32: Device | C32: Capacity (Wh) | D32: Cranking hours
B33: Phone, 4000 mAh at 3.85 V | C33: 15.4 | D33: =C33/E29 -> 1.2789957
B34: Tablet | C34: 25 | D34: =C34/E29 -> 2.0762918
B35: 20 000 mAh power bank | C35: 74 | D35: =C35/E29 -> 6.1458236
B36: Laptop, small | C36: 50 | D36: =C36/E29 -> 4.1525835
B38: Output band at the pull-out limits
B39: At LS pull-out low | C39: =D9*2*PI()*D6/60 -> 16.9646 | D39: =C39*C23*C24*C25*C26*C27*C28 -> 9.0305227 | H39: Mechanical W in (col C) -> USB W out (col D). Exceed pull-out and the gear simply slips - it cannot shear a tooth.
B40: At LS pull-out high | C40: =D10*2*PI()*D6/60 -> 28.274334 | D40: =C40*C23*C24*C25*C26*C27*C28 -> 15.050871 | H40: Mechanical W in (col C) -> USB W out (col D). Exceed pull-out and the gear simply slips - it cannot shear a tooth.
B42: Scaling: torque is proportional to active volume at 12-20 N.m/L
B43: Active volume (L) | C43: LS torque low (N.m) | D43: LS torque high (N.m) | E43: Mech W at set rpm, low | F43: Mech W high
B44: 0.15 | C44: =B44*12 -> 1.8 | D44: =B44*20 -> 3 | E44: =C44*2*PI()*D6/60 -> 16.9646 | F44: =D44*2*PI()*D6/60 -> 28.274334
B45: 0.3 | C45: =B45*12 -> 3.6 | D45: =B45*20 -> 6 | E45: =C45*2*PI()*D6/60 -> 33.929201 | F45: =D45*2*PI()*D6/60 -> 56.548668
B46: 0.5 | C46: =B46*12 -> 6 | D46: =B46*20 -> 10 | E46: =C46*2*PI()*D6/60 -> 56.548668 | F46: =D46*2*PI()*D6/60 -> 94.24778
B47: 1 | C47: =B47*12 -> 12 | D47: =B47*20 -> 20 | E47: =C47*2*PI()*D6/60 -> 113.09734 | F47: =D47*2*PI()*D6/60 -> 188.49556
B48: 0.150 L is MG-1 as drawn. Want 50 W at the port? That needs roughly a 0.4-0.5 L active volume, i.e. a physically larger gear - not a better winding.

Sheet Sources
B2: SOURCES
B3: Researched lines only. Unsourced prices are engineering estimates and are labelled as such.
B5: BOM ref / claim | C5: Source | D5: URL
B6: B1 magnet price and spec | C6: supermagnete Q-20-10-05-N, N42 20x10x5, EUR1.26 ea from 40 pcs | D6: https://www.supermagnete.de/eng/block-magnets-neodymium/block-magnet-20mm-10mm-5mm_Q-20-10-05-N
B7: C6 bearing price | C7: NSK 608ZZ 10-pack, USD20.65 (USD2.07 ea), Amazon | D7: https://www.amazon.com/dp/B07P4NQZ8Q
B8: D1 hub motor price | C8: Hub motor for 6.5in hoverboards, USD106.99, Monster Scooter Parts | D8: https://monsterscooterparts.com/products/hub-motor-for-self-balancing-hoverboards-with-6-5-tires
B9: E3 LT4320 price + spec | C9: Analog Devices LT4320 ideal diode bridge controller, from USD4.07 at 1ku | D9: https://www.analog.com/en/products/lt4320.html
B10: E3 bridge efficiency | C10: LT4320 3-phase demo: 84% for a diode bridge vs 97% for the ideal diode bridge at 5 VAC L-N, 25 A | D10: https://www.analog.com/media/en/technical-documentation/user-guides/dc2465af.pdf
B11: E7 LTC4020 price + spec | C11: Analog Devices LTC4020, 4.5-55 V in, buck-boost multi-chemistry charger, from USD6.79 at 1ku | D11: https://www.analog.com/en/products/ltc4020.html
B12: Human input power | C12: Jansen & Slob, 'Human power: comfortable one-hand cranking', ICED 2003 - sustained 54 +/- 14 W | D12: https://www.designsociety.org/download-publication/23972/human_power_comfortable_one-_hand_cranking
B13: G3 polarity probe | C13: Indigo Instruments Mark II Magnaprobe - confirms magnets are positioned with poles pointing correctly | D13: https://www.indigoinstruments.com/magnets/rare_earth/blocks/ndfeb-block-magnet-20x10x5mm-44251-5.html
B14: Torque density basis | C14: Sheffield PDD thesis: PDD 60-90 N.m/L air-cooled vs 10-30 for conventional PM machines | D14: https://etheses.whiterose.ac.uk/id/eprint/24379/1/PhD_Main_DOC_v64_Final_with_Appendix_corrected.pdf
B15: Gear topology | C15: Atallah & Howe, flux-modulated magnetic gear, J. Magn. Magn. Mater. | D15: https://www.sciencedirect.com/science/article/abs/pii/S0304885303022182
B16: Torque-fuse precedent | C16: Magnomatics Pseudo Direct Drive - inherent torque limit, <60% size/mass of a PM machine | D16: https://www.magnomatics.com/technology/pseudo-direct-drive
